{
  "scriptId": "439",
  "url": "file:///Users/guy/Workspace/@sitebender/engine-ai/node_modules/.deno/fast-check@4.3.0/node_modules/fast-check/lib/utils/stringify.js",
  "functions": [
    {
      "functionName": "",
      "ranges": [
        { "startOffset": 0, "endOffset": 11126, "count": 1 },
        { "startOffset": 276, "endOffset": 287, "count": 0 }
      ],
      "isBlockCoverage": true
    },
    {
      "functionName": "hasToStringMethod",
      "ranges": [{ "startOffset": 795, "endOffset": 1039, "count": 0 }],
      "isBlockCoverage": false
    },
    {
      "functionName": "hasAsyncToStringMethod",
      "ranges": [{ "startOffset": 1128, "endOffset": 1387, "count": 0 }],
      "isBlockCoverage": false
    },
    {
      "functionName": "getSymbolDescription",
      "ranges": [{ "startOffset": 1436, "endOffset": 1633, "count": 0 }],
      "isBlockCoverage": false
    },
    {
      "functionName": "stringifyNumber",
      "ranges": [{ "startOffset": 1634, "endOffset": 2046, "count": 0 }],
      "isBlockCoverage": false
    },
    {
      "functionName": "isSparseArray",
      "ranges": [{ "startOffset": 2047, "endOffset": 2378, "count": 0 }],
      "isBlockCoverage": false
    },
    {
      "functionName": "stringifyInternal",
      "ranges": [{ "startOffset": 2386, "endOffset": 8970, "count": 0 }],
      "isBlockCoverage": false
    },
    {
      "functionName": "stringify",
      "ranges": [{ "startOffset": 8978, "endOffset": 9096, "count": 0 }],
      "isBlockCoverage": false
    },
    {
      "functionName": "possiblyAsyncStringify",
      "ranges": [{ "startOffset": 9104, "endOffset": 11018, "count": 0 }],
      "isBlockCoverage": false
    },
    {
      "functionName": "asyncStringify",
      "ranges": [{ "startOffset": 11026, "endOffset": 11125, "count": 0 }],
      "isBlockCoverage": false
    }
  ]
}
