{
  "scriptId": "333",
  "url": "file:///Users/guy/Workspace/test/dasl/tests/build/handlesErrorConditions/index.test.ts",
  "functions": [
    {
      "functionName": "",
      "ranges": [{ "startOffset": 0, "endOffset": 6034, "count": 1 }],
      "isBlockCoverage": true
    },
    {
      "functionName": "cleanTestOutput",
      "ranges": [
        { "startOffset": 220, "endOffset": 396, "count": 4 },
        { "startOffset": 333, "endOffset": 394, "count": 2 }
      ],
      "isBlockCoverage": true
    },
    {
      "functionName": "backupSource",
      "ranges": [
        { "startOffset": 397, "endOffset": 690, "count": 3 },
        { "startOffset": 502, "endOffset": 507, "count": 0 },
        { "startOffset": 620, "endOffset": 688, "count": 0 }
      ],
      "isBlockCoverage": true
    },
    {
      "functionName": "restoreSource",
      "ranges": [
        { "startOffset": 691, "endOffset": 945, "count": 3 },
        { "startOffset": 794, "endOffset": 799, "count": 2 },
        { "startOffset": 799, "endOffset": 846, "count": 1 },
        { "startOffset": 903, "endOffset": 943, "count": 0 }
      ],
      "isBlockCoverage": true
    },
    {
      "functionName": "createMinimalSource",
      "ranges": [{ "startOffset": 946, "endOffset": 1786, "count": 2 }],
      "isBlockCoverage": true
    },
    {
      "functionName": "fileExists",
      "ranges": [
        { "startOffset": 1787, "endOffset": 1909, "count": 2 },
        { "startOffset": 1877, "endOffset": 1907, "count": 0 }
      ],
      "isBlockCoverage": true
    },
    {
      "functionName": "runBuildWithErrors",
      "ranges": [
        { "startOffset": 1910, "endOffset": 2276, "count": 5 },
        { "startOffset": 2257, "endOffset": 2275, "count": 4 }
      ],
      "isBlockCoverage": true
    },
    {
      "functionName": "log",
      "ranges": [{ "startOffset": 1997, "endOffset": 2003, "count": 0 }],
      "isBlockCoverage": false
    },
    {
      "functionName": "info",
      "ranges": [{ "startOffset": 2015, "endOffset": 2021, "count": 0 }],
      "isBlockCoverage": false
    },
    {
      "functionName": "warn",
      "ranges": [{ "startOffset": 2033, "endOffset": 2086, "count": 0 }],
      "isBlockCoverage": false
    },
    {
      "functionName": "error",
      "ranges": [{ "startOffset": 2099, "endOffset": 2152, "count": 0 }],
      "isBlockCoverage": false
    },
    {
      "functionName": "",
      "ranges": [{ "startOffset": 2321, "endOffset": 6031, "count": 1 }],
      "isBlockCoverage": true
    },
    {
      "functionName": "",
      "ranges": [{ "startOffset": 2433, "endOffset": 2932, "count": 1 }],
      "isBlockCoverage": true
    },
    {
      "functionName": "",
      "ranges": [{ "startOffset": 3000, "endOffset": 3271, "count": 1 }],
      "isBlockCoverage": true
    },
    {
      "functionName": "",
      "ranges": [{ "startOffset": 3172, "endOffset": 3208, "count": 1 }],
      "isBlockCoverage": true
    },
    {
      "functionName": "",
      "ranges": [{ "startOffset": 3332, "endOffset": 4311, "count": 1 }],
      "isBlockCoverage": true
    },
    {
      "functionName": "",
      "ranges": [{ "startOffset": 4377, "endOffset": 5191, "count": 1 }],
      "isBlockCoverage": true
    },
    {
      "functionName": "",
      "ranges": [{ "startOffset": 5265, "endOffset": 5971, "count": 1 }],
      "isBlockCoverage": true
    }
  ]
}
